pythopia/__init__.py
pythopia/ethiopian_cal.py
pythopia/tests.py
pythopia-1.0.0.dist-info/METADATA
pythopia-1.0.0.dist-info/WHEEL
pythopia-1.0.0.dist-info/top_level.txt
pythopia-1.0.0.dist-info/RECORD
