Metadata-Version: 2.1
Name: pythopia
Version: 1.0.0
Summary: Ethiopian date converter.
Home-page: http://github.com/nuradic/pythopia
Author: Murad
Author-email: nuradhussen082@gmail.com
License: GNU General Public License (GPL), Version 3
Classifier: Development Status :: 4 - Beta
Classifier: Intended Audience :: Developers
Classifier: License :: OSI Approved :: GNU Library or Lesser General Public License (LGPL)
Classifier: Programming Language :: Python
Provides: pythopia
Requires-Dist: six >=1.11.0
